LICENSE
MANIFEST.in
README.md
pyproject.toml
setup.py
grigora/__init__.py
grigora.egg-info/PKG-INFO
grigora.egg-info/SOURCES.txt
grigora.egg-info/dependency_links.txt
grigora.egg-info/not-zip-safe
grigora.egg-info/requires.txt
grigora.egg-info/top_level.txt
grigora/keras/__init__.py
grigora/keras/preprocessing/__init__.py
grigora/keras/preprocessing/cython_skipgrams.c
grigora/keras/preprocessing/cython_skipgrams.pyx
grigora/keras/preprocessing/sequence.py
test/keras/sequence_test.py